__init__.py
cli/__init__.py
cli/main.py
config/criteria.yaml
config/loader.py
core/__init__.py
core/badge.py
core/model.py
core/scorer.py
devops_maturity-0.3.0.dist-info/licenses/LICENSE
web/__init__.py
web/main.py
devops_maturity-0.3.0.dist-info/METADATA
devops_maturity-0.3.0.dist-info/WHEEL
devops_maturity-0.3.0.dist-info/entry_points.txt
devops_maturity-0.3.0.dist-info/top_level.txt
devops_maturity-0.3.0.dist-info/RECORD
