Metadata-Version: 2.4
Name: devops-maturity
Version: 0.3.0
Summary: A tool to evaluate and measure the maturity level of your DevOps practices.
Author-email: Xianpeng Shen <xianpeng.shen@gmail.com>
License-Expression: Apache-2.0
Project-URL: homepage, https://github.com/devops-maturity
Project-URL: source, https://github.com/devops-maturity/devops-maturity
Project-URL: tracker, https://github.com/devops-maturity/devops-maturity/issues
Keywords: devops,maturity,assessment,cli
Classifier: Development Status :: 3 - Alpha
Classifier: Intended Audience :: Developers
Classifier: Programming Language :: Python :: 3.9
Classifier: Programming Language :: Python :: 3.10
Classifier: Programming Language :: Python :: 3.11
Classifier: Programming Language :: Python :: 3.12
Classifier: Programming Language :: Python :: 3.13
Requires-Python: >=3.9
License-File: LICENSE
Requires-Dist: fastapi
Requires-Dist: typer
Requires-Dist: jinja2
Requires-Dist: pydantic
Requires-Dist: pyyaml
Requires-Dist: python-multipart
Requires-Dist: sqlalchemy
Requires-Dist: passlib[bcrypt]==1.7.4
Requires-Dist: bcrypt==4.3.0
Requires-Dist: authlib
Requires-Dist: python-dotenv
Requires-Dist: itsdangerous
Requires-Dist: httpx
Requires-Dist: uvicorn
Provides-Extra: dev
Requires-Dist: ruff; extra == "dev"
Requires-Dist: uvicorn; extra == "dev"
Provides-Extra: test
Requires-Dist: fastapi; extra == "test"
Requires-Dist: httpx; extra == "test"
Requires-Dist: pytest; extra == "test"
Requires-Dist: pytest-cov; extra == "test"
Dynamic: license-file
